neuropy3/__init__.py
neuropy3/__main__.py
neuropy3/neuropy3.py
neuropy3/utils.py
neuropy3/gui/__init__.py
neuropy3/gui/gui.py
neuropy3/gui/resources.py
neuropy3-1.0.4.dist-info/LICENSE
neuropy3-1.0.4.dist-info/METADATA
neuropy3-1.0.4.dist-info/WHEEL
neuropy3-1.0.4.dist-info/entry_points.txt
neuropy3-1.0.4.dist-info/top_level.txt
neuropy3-1.0.4.dist-info/RECORD
