Metadata-Version: 2.1
Name: neuropy3
Version: 1.0.4
Summary: Python3 library to read data from Neurosky Mindwave Mobile 2 in linux.
Home-page: https://gitlab.gast.it.uc3m.es/schica/neuropy3
Author: Sergio Chica
Author-email: sergio.chica@uc3m.es
License: GPLv3+
Keywords: eeg,neurosky,mindwave,neurosky mindwave mobile 2
Classifier: License :: OSI Approved :: GNU General Public License v3 or later (GPLv3+)
Classifier: Programming Language :: Python :: 3
Classifier: Programming Language :: Python :: 3.8
Requires-Python: >= 3.8
License-File: LICENSE
Requires-Dist: pybluez2 (==0.46)
Requires-Dist: numpy (==1.23.3)
Requires-Dist: scipy (==1.9.1)
Provides-Extra: gui
Requires-Dist: PySide6 (==6.2.3) ; extra == 'gui'
Requires-Dist: shiboken6 (==6.2.3) ; extra == 'gui'
